mssql_mcp_server/__init__.py
mssql_mcp_server/__main__.py
mssql_mcp_server/server.py
iflow_mcp_microsoft_sql_server_mcp-0.1.0.dist-info/METADATA
iflow_mcp_microsoft_sql_server_mcp-0.1.0.dist-info/WHEEL
iflow_mcp_microsoft_sql_server_mcp-0.1.0.dist-info/entry_points.txt
iflow_mcp_microsoft_sql_server_mcp-0.1.0.dist-info/licenses/LICENSE
iflow_mcp_microsoft_sql_server_mcp-0.1.0.dist-info/RECORD
